{"Impressionism": 0.0060164961266844, "style": ["Expressionism", "Expressionism", "Expressionism", "Expressionism", "Neo-Expressionism", "Baroque", "Surrealism", "Art Nouveau (Modern)", "Art Nouveau (Modern)", "Abstract Expressionism", "Art Nouveau (Modern)", "Art Nouveau (Modern)", "Constructivism", "Expressionism", "Abstract Art", "Expressionism", "Impressionism", "Baroque", "Art Nouveau (Modern)", "Regionalism"], "Abstract Expressionism": 0.005473792959041323, "Neo-Expressionism": 0.004504411461841984, "contentId": ["232801.jpg", "232759.jpg", "232621.jpg", "232736.jpg", "231509.jpg", "220130.jpg", "221033.jpg", "230520.jpg", "230373.jpg", "290260.jpg", "230489.jpg", "232710.jpg", "219879.jpg", "232685.jpg", "189424.jpg", "251874.jpg", "213683.jpg", "220131.jpg", "230395.jpg", "247842.jpg"], "Art Nouveau (Modern)": 0.005253116374638865, "artist": ["Schiele Egon", "Schiele Egon", "Schiele Egon", "Schiele Egon", "Twombly Cy", "Rembrandt", "Dali Salvador", "Toulouse-Lautrec Henri de", "Toulouse-Lautrec Henri de", "Matisse Henri", "Toulouse-Lautrec Henri de", "Schiele Egon", "Malevich Kazimir", "Schiele Egon", "Kandinsky Wassily", "Kirchner Ernst Ludwig", "Degas Edgar", "Rembrandt", "Toulouse-Lautrec Henri de", "Rockwell Norman"], "year": [1913.0, 1910.0, 1910.0, 1913.0, 2009.0, 1664.0, 1940.0, 1895.0, 1892.0, 1950.0, 1893.0, 1910.0, 1913.0, 1910.0, 1916.0, 1926.0, 1904.0, 1664.0, 1896.0, 1934.0], "style_counts": [0.00010533621291308748, 0.0006480393805562423, 0.0016174208777555155, 0.0008687159649586329, 0.0008911353770852948, 0.001953654816472916, 0.0004020602635553816, 0.0003568206933133311, 0.000595230614046538, 0.0], "Surrealism": 0.005230696962512229, "style_labels": ["Impressionism", "Abstract Expressionism", "Neo-Expressionism", "Art Nouveau (Modern)", "Surrealism", "Expressionism", "Constructivism", "Abstract Art", "Baroque", "Regionalism"], "title": ["Standing Woman in Red", "Self Portrait", "Female Nude", "Rufer", "Leaving Paphos Ringed With Waves V", "Elsje Christiaens", "Group of Women Imitating the Gestures of a Schooner", "Miss May Belfort", "At the Music Hall Loie Fuller", "Japanese Mask", "M. Praince", "Portrait of Madame Dr. Horak", "The Athlete of the Future", "Poldi Lodzinsky", "To the Unknown Voice", "Dance Group of the Mary Wigman School in Dresden", "Study for a Portrait", "Elsje Christiaens", "Chocolat dancing in the Irish and American Bar", "Tiny Tim and Bob Cratchit"], "Expressionism": 0.0041681775231246256, "Constructivism": 0.0057197720760420985, "scores": [0.008314964715820843, 0.011791600163901947, 0.012392144372830309, 0.01257697468198703, 0.013019423675251846, 0.015047609323400699, 0.015118658774558598, 0.015680057450509557, 0.015748176623958166, 0.015821296577383917, 0.016081746380768994, 0.01614326487029908, 0.016532267670195194, 0.016557539055393686, 0.0166630268463624, 0.0167825560984051, 0.017389910486060253, 0.01749787376268109, 0.0175347833066665, 0.017694371300948093], "Abstract Art": 0.005765011646284226, "Baroque": 0.005526601725551007, "style_dict": {"Impressionism": 1, "Abstract Expressionism": 1, "Neo-Expressionism": 1, "Art Nouveau (Modern)": 5, "Surrealism": 1, "Expressionism": 6, "Abstract Art": 1, "Constructivism": 1, "Baroque": 2, "Regionalism": 1}, "Regionalism": 0.006121832339597527}