{"Impressionism": 0.0034938299536646645, "style": ["Surrealism", "Surrealism", "Surrealism", "Art Nouveau (Modern)", "Expressionism, Symbolism", "Surrealism", "Expressionism", "Abstract Expressionism, Symbolism", "Art Nouveau (Modern)", "Impressionism", "Realism", "Art Nouveau (Modern)", "Art Nouveau (Modern)", "Surrealism", "Na\u00efve Art (Primitivism)", "Surrealism", "Na\u00efve Art (Primitivism)", "Realism", "Realism", "Realism"], "style_labels": ["Impressionism", "Art Nouveau (Modern)", "Surrealism", "Abstract Expressionism, Symbolism", "Expressionism, Symbolism", "Na\u00efve Art (Primitivism)", "Expressionism", "Realism"], "artist": ["Picasso Pablo", "Beksinski Zdislav", "Beksinski Zdislav", "Roerich Nicholas", "Dali Salvador", "Beksinski Zdislav", "Serebriakova Zinaida", "Dali Salvador", "Kustodiev Boris", "Renoir Pierre-Auguste", "Kustodiev Boris", "Serebriakova Zinaida", "Kustodiev Boris", "Dali Salvador", "Chagall Marc", "Freud Lucian", "Chagall Marc", "Sargent John Singer", "Toulouse-Lautrec Henri de", "Roerich Nicholas"], "contentId": ["224629.jpg", "259015.jpg", "259003.jpg", "226128.jpg", "246719.jpg", "258879.jpg", "227441.jpg", "246747.jpg", "229943.jpg", "219521.jpg", "230185.jpg", "227272.jpg", "229688.jpg", "220879.jpg", "202358.jpg", "231958.jpg", "202744.jpg", "266434.jpg", "230343.jpg", "227052.jpg"], "Art Nouveau (Modern)": 0.0031436866186681195, "title": ["Tomato plant", "Untitled", "Untitled", "Mariners", "Da mihi bibere (Ecclesiastes 12:1)", "Untitled", "Portrait of Sergei Rostislavovich Ernst", "Iesus flagellatus (John 19:1)", "Pancake Tuesday in a Village. Maslenitsa", "Young Girl Slipping on Her Stockings", "Seated Model", "India", "A merchant in a fur coat", "Corpuscular Madonna", "A Big Peasant", "Fragment Head of Gerald Wilde", "Madame Sobakevitch", "Nude 2", "Academic Study Nude", "Voivode"], "style_counts": [8.281686777245056e-06, 0.000358425021773745, 0.0008036277167396966, 0.00026794522174977686, 0.0006389278472198612, 0.0, 0.0004872259076975638, 7.759485365621543e-05], "Surrealism": 0.002698483923702162, "Abstract Expressionism, Symbolism": 0.0032341664186920738, "Expressionism, Symbolism": 0.0028631837932220445, "Na\u00efve Art (Primitivism)": 0.003502111640441909, "Expressionism": 0.0030148857327443285, "year": [1944.0, "unknown", "unknown", 1912.0, 1967.0, "unknown", 1921.0, 1964.0, 1916.0, 1895.0, 1898.0, 1916.0, 1920.0, 1952.0, 1968.0, 1943.0, 1923.0, "unknown", 1883.0, 1896.0], "scores": [0.006608080368811145, 0.007181711232573908, 0.008036840535329631, 0.008108834359189722, 0.00827566557359501, 0.008467321897003532, 0.008714140575208291, 0.009347943276923752, 0.009940005009912638, 0.010098467424964012, 0.010104908953121515, 0.010110756970531425, 0.01012450145119009, 0.010157256458838523, 0.010203556314238239, 0.010315273914718799, 0.010419951732781128, 0.0104519915639816, 0.010567044736144273, 0.01058012752967072], "style_dict": {"Impressionism": 1, "Art Nouveau (Modern)": 4, "Surrealism": 6, "Abstract Expressionism, Symbolism": 1, "Expressionism, Symbolism": 1, "Na\u00efve Art (Primitivism)": 2, "Expressionism": 1, "Realism": 4}, "Realism": 0.0034245167867856816}